{
  "title": "Editing & Publishing with Precision",
  "objective": "Edit for grammar, punctuation, and clarity before publishing.",
  "standards": [],
  "skills_tested": [
    "revision",
    "mechanics",
    "clarity"
  ],
  "lessons": [
    {
      "title": "Understanding Media Messages",
      "bloom_level": "Understand",
      "skills_tested": [],
      "steps": [
        {
          "type": "hook",
          "content": "",
          "media": {}
        },
        {
          "type": "concept",
          "content": "",
          "media": {}
        },
        {
          "type": "guided_practice",
          "content": "",
          "media": {}
        },
        {
          "type": "try_it",
          "content": "",
          "media": {}
        },
        {
          "type": "wrap_up",
          "content": "",
          "media": {}
        }
      ],
      "id": "4_ELA_unit_11_lesson_01"
    },
    {
      "title": "Comparing News and Opinions",
      "bloom_level": "Understand",
      "skills_tested": [],
      "steps": [
        {
          "type": "hook",
          "content": "",
          "media": {}
        },
        {
          "type": "concept",
          "content": "",
          "media": {}
        },
        {
          "type": "guided_practice",
          "content": "",
          "media": {}
        },
        {
          "type": "try_it",
          "content": "",
          "media": {}
        },
        {
          "type": "wrap_up",
          "content": "",
          "media": {}
        }
      ],
      "id": "4_ELA_unit_11_lesson_02"
    },
    {
      "title": "Identifying Target Audience",
      "bloom_level": "Apply",
      "skills_tested": [],
      "steps": [
        {
          "type": "hook",
          "content": "",
          "media": {}
        },
        {
          "type": "concept",
          "content": "",
          "media": {}
        },
        {
          "type": "guided_practice",
          "content": "",
          "media": {}
        },
        {
          "type": "try_it",
          "content": "",
          "media": {}
        },
        {
          "type": "wrap_up",
          "content": "",
          "media": {}
        }
      ],
      "id": "4_ELA_unit_11_lesson_03"
    },
    {
      "title": "Analyzing Persuasive Techniques",
      "bloom_level": "Apply",
      "skills_tested": [],
      "steps": [
        {
          "type": "hook",
          "content": "",
          "media": {}
        },
        {
          "type": "concept",
          "content": "",
          "media": {}
        },
        {
          "type": "guided_practice",
          "content": "",
          "media": {}
        },
        {
          "type": "try_it",
          "content": "",
          "media": {}
        },
        {
          "type": "wrap_up",
          "content": "",
          "media": {}
        }
      ],
      "id": "4_ELA_unit_11_lesson_04"
    },
    {
      "title": "Evaluating Digital Sources",
      "bloom_level": "Apply",
      "skills_tested": [],
      "steps": [
        {
          "type": "hook",
          "content": "",
          "media": {}
        },
        {
          "type": "concept",
          "content": "",
          "media": {}
        },
        {
          "type": "guided_practice",
          "content": "",
          "media": {}
        },
        {
          "type": "try_it",
          "content": "",
          "media": {}
        },
        {
          "type": "wrap_up",
          "content": "",
          "media": {}
        }
      ],
      "id": "4_ELA_unit_11_lesson_05"
    },
    {
      "title": "Reviewing Website Credibility",
      "bloom_level": "Analyze",
      "skills_tested": [],
      "steps": [
        {
          "type": "hook",
          "content": "",
          "media": {}
        },
        {
          "type": "concept",
          "content": "",
          "media": {}
        },
        {
          "type": "guided_practice",
          "content": "",
          "media": {}
        },
        {
          "type": "try_it",
          "content": "",
          "media": {}
        },
        {
          "type": "wrap_up",
          "content": "",
          "media": {}
        }
      ],
      "id": "4_ELA_unit_11_lesson_06"
    },
    {
      "title": "Creating a Media Log",
      "bloom_level": "Apply",
      "skills_tested": [],
      "steps": [
        {
          "type": "hook",
          "content": "",
          "media": {}
        },
        {
          "type": "concept",
          "content": "",
          "media": {}
        },
        {
          "type": "guided_practice",
          "content": "",
          "media": {}
        },
        {
          "type": "try_it",
          "content": "",
          "media": {}
        },
        {
          "type": "wrap_up",
          "content": "",
          "media": {}
        }
      ],
      "id": "4_ELA_unit_11_lesson_07"
    },
    {
      "title": "Watching Media with Critical Eye",
      "bloom_level": "Apply",
      "skills_tested": [],
      "steps": [
        {
          "type": "hook",
          "content": "",
          "media": {}
        },
        {
          "type": "concept",
          "content": "",
          "media": {}
        },
        {
          "type": "guided_practice",
          "content": "",
          "media": {}
        },
        {
          "type": "try_it",
          "content": "",
          "media": {}
        },
        {
          "type": "wrap_up",
          "content": "",
          "media": {}
        }
      ],
      "id": "4_ELA_unit_11_lesson_08"
    },
    {
      "title": "Writing Media Responses",
      "bloom_level": "Evaluate",
      "skills_tested": [],
      "steps": [
        {
          "type": "hook",
          "content": "",
          "media": {}
        },
        {
          "type": "concept",
          "content": "",
          "media": {}
        },
        {
          "type": "guided_practice",
          "content": "",
          "media": {}
        },
        {
          "type": "try_it",
          "content": "",
          "media": {}
        },
        {
          "type": "wrap_up",
          "content": "",
          "media": {}
        }
      ],
      "id": "4_ELA_unit_11_lesson_09"
    },
    {
      "title": "Discussing Media Bias",
      "bloom_level": "Create",
      "skills_tested": [],
      "steps": [
        {
          "type": "hook",
          "content": "",
          "media": {}
        },
        {
          "type": "concept",
          "content": "",
          "media": {}
        },
        {
          "type": "guided_practice",
          "content": "",
          "media": {}
        },
        {
          "type": "try_it",
          "content": "",
          "media": {}
        },
        {
          "type": "wrap_up",
          "content": "",
          "media": {}
        }
      ],
      "id": "4_ELA_unit_11_lesson_10"
    },
    {
      "title": "Designing a Public Service Message",
      "bloom_level": "Analyze",
      "skills_tested": [],
      "steps": [
        {
          "type": "hook",
          "content": "",
          "media": {}
        },
        {
          "type": "concept",
          "content": "",
          "media": {}
        },
        {
          "type": "guided_practice",
          "content": "",
          "media": {}
        },
        {
          "type": "try_it",
          "content": "",
          "media": {}
        },
        {
          "type": "wrap_up",
          "content": "",
          "media": {}
        }
      ],
      "id": "4_ELA_unit_11_lesson_11"
    },
    {
      "title": "Writing a Commercial Script",
      "bloom_level": "Create",
      "skills_tested": [],
      "steps": [
        {
          "type": "hook",
          "content": "",
          "media": {}
        },
        {
          "type": "concept",
          "content": "",
          "media": {}
        },
        {
          "type": "guided_practice",
          "content": "",
          "media": {}
        },
        {
          "type": "try_it",
          "content": "",
          "media": {}
        },
        {
          "type": "wrap_up",
          "content": "",
          "media": {}
        }
      ],
      "id": "4_ELA_unit_11_lesson_12"
    },
    {
      "title": "Revising Media Scripts",
      "bloom_level": "Create",
      "skills_tested": [],
      "steps": [
        {
          "type": "hook",
          "content": "",
          "media": {}
        },
        {
          "type": "concept",
          "content": "",
          "media": {}
        },
        {
          "type": "guided_practice",
          "content": "",
          "media": {}
        },
        {
          "type": "try_it",
          "content": "",
          "media": {}
        },
        {
          "type": "wrap_up",
          "content": "",
          "media": {}
        }
      ],
      "id": "4_ELA_unit_11_lesson_13"
    },
    {
      "title": "Filming or Presenting Messages",
      "bloom_level": "Apply",
      "skills_tested": [],
      "steps": [
        {
          "type": "hook",
          "content": "",
          "media": {}
        },
        {
          "type": "concept",
          "content": "",
          "media": {}
        },
        {
          "type": "guided_practice",
          "content": "",
          "media": {}
        },
        {
          "type": "try_it",
          "content": "",
          "media": {}
        },
        {
          "type": "wrap_up",
          "content": "",
          "media": {}
        }
      ],
      "id": "4_ELA_unit_11_lesson_14"
    },
    {
      "title": "Building a Media Critique Gallery",
      "bloom_level": "Evaluate",
      "skills_tested": [],
      "steps": [
        {
          "type": "hook",
          "content": "",
          "media": {}
        },
        {
          "type": "concept",
          "content": "",
          "media": {}
        },
        {
          "type": "guided_practice",
          "content": "",
          "media": {}
        },
        {
          "type": "try_it",
          "content": "",
          "media": {}
        },
        {
          "type": "wrap_up",
          "content": "",
          "media": {}
        }
      ],
      "id": "4_ELA_unit_11_lesson_15"
    },
    {
      "title": "Peer Feedback on Messages",
      "bloom_level": "Create",
      "skills_tested": [],
      "steps": [
        {
          "type": "hook",
          "content": "",
          "media": {}
        },
        {
          "type": "concept",
          "content": "",
          "media": {}
        },
        {
          "type": "guided_practice",
          "content": "",
          "media": {}
        },
        {
          "type": "try_it",
          "content": "",
          "media": {}
        },
        {
          "type": "wrap_up",
          "content": "",
          "media": {}
        }
      ],
      "id": "4_ELA_unit_11_lesson_16"
    },
    {
      "title": "Writing Reflections on Media",
      "bloom_level": "Evaluate",
      "skills_tested": [],
      "steps": [
        {
          "type": "hook",
          "content": "",
          "media": {}
        },
        {
          "type": "concept",
          "content": "",
          "media": {}
        },
        {
          "type": "guided_practice",
          "content": "",
          "media": {}
        },
        {
          "type": "try_it",
          "content": "",
          "media": {}
        },
        {
          "type": "wrap_up",
          "content": "",
          "media": {}
        }
      ],
      "id": "4_ELA_unit_11_lesson_17"
    },
    {
      "title": "Publishing Multimedia Projects",
      "bloom_level": "Reflect",
      "skills_tested": [],
      "steps": [
        {
          "type": "hook",
          "content": "",
          "media": {}
        },
        {
          "type": "concept",
          "content": "",
          "media": {}
        },
        {
          "type": "guided_practice",
          "content": "",
          "media": {}
        },
        {
          "type": "try_it",
          "content": "",
          "media": {}
        },
        {
          "type": "wrap_up",
          "content": "",
          "media": {}
        }
      ],
      "id": "4_ELA_unit_11_lesson_18"
    },
    {
      "title": "Sharing in a Media Fair",
      "bloom_level": "Apply",
      "skills_tested": [],
      "steps": [
        {
          "type": "hook",
          "content": "",
          "media": {}
        },
        {
          "type": "concept",
          "content": "",
          "media": {}
        },
        {
          "type": "guided_practice",
          "content": "",
          "media": {}
        },
        {
          "type": "try_it",
          "content": "",
          "media": {}
        },
        {
          "type": "wrap_up",
          "content": "",
          "media": {}
        }
      ],
      "id": "4_ELA_unit_11_lesson_19"
    },
    {
      "title": "Celebrating Media Savvy",
      "bloom_level": "Celebrate",
      "skills_tested": [],
      "steps": [
        {
          "type": "hook",
          "content": "",
          "media": {}
        },
        {
          "type": "concept",
          "content": "",
          "media": {}
        },
        {
          "type": "guided_practice",
          "content": "",
          "media": {}
        },
        {
          "type": "try_it",
          "content": "",
          "media": {}
        },
        {
          "type": "wrap_up",
          "content": "",
          "media": {}
        }
      ],
      "id": "4_ELA_unit_11_lesson_20"
    }
  ],
  "id": "4_ELA_unit_11"
}