{
  "title": "Comprehension Check-In",
  "objective": "Strengthen story understanding through simple questions and discussion.",
  "standards": [],
  "skills_tested": [
    "comprehension",
    "answering questions",
    "verbal recall"
  ],
  "lessons": [
    {
      "title": "What Is a Character?",
      "bloom_level": "Remember",
      "skills_tested": [],
      "steps": [
        {
          "type": "hook",
          "content": "",
          "media": {}
        },
        {
          "type": "concept",
          "content": "",
          "media": {}
        },
        {
          "type": "guided_practice",
          "content": "",
          "media": {}
        },
        {
          "type": "try_it",
          "content": "",
          "media": {}
        },
        {
          "type": "wrap_up",
          "content": "",
          "media": {}
        }
      ],
      "id": "k_Reading_unit_04_lesson_01"
    },
    {
      "title": "Identifying Characters in Picture Books",
      "bloom_level": "Understand",
      "skills_tested": [],
      "steps": [
        {
          "type": "hook",
          "content": "",
          "media": {}
        },
        {
          "type": "concept",
          "content": "",
          "media": {}
        },
        {
          "type": "guided_practice",
          "content": "",
          "media": {}
        },
        {
          "type": "try_it",
          "content": "",
          "media": {}
        },
        {
          "type": "wrap_up",
          "content": "",
          "media": {}
        }
      ],
      "id": "k_Reading_unit_04_lesson_02"
    },
    {
      "title": "Describing Characters by Actions",
      "bloom_level": "Apply",
      "skills_tested": [],
      "steps": [
        {
          "type": "hook",
          "content": "",
          "media": {}
        },
        {
          "type": "concept",
          "content": "",
          "media": {}
        },
        {
          "type": "guided_practice",
          "content": "",
          "media": {}
        },
        {
          "type": "try_it",
          "content": "",
          "media": {}
        },
        {
          "type": "wrap_up",
          "content": "",
          "media": {}
        }
      ],
      "id": "k_Reading_unit_04_lesson_03"
    },
    {
      "title": "Matching Emotions to Characters",
      "bloom_level": "Apply",
      "skills_tested": [],
      "steps": [
        {
          "type": "hook",
          "content": "",
          "media": {}
        },
        {
          "type": "concept",
          "content": "",
          "media": {}
        },
        {
          "type": "guided_practice",
          "content": "",
          "media": {}
        },
        {
          "type": "try_it",
          "content": "",
          "media": {}
        },
        {
          "type": "wrap_up",
          "content": "",
          "media": {}
        }
      ],
      "id": "k_Reading_unit_04_lesson_04"
    },
    {
      "title": "Drawing a Character’s Face",
      "bloom_level": "Apply",
      "skills_tested": [],
      "steps": [
        {
          "type": "hook",
          "content": "",
          "media": {}
        },
        {
          "type": "concept",
          "content": "",
          "media": {}
        },
        {
          "type": "guided_practice",
          "content": "",
          "media": {}
        },
        {
          "type": "try_it",
          "content": "",
          "media": {}
        },
        {
          "type": "wrap_up",
          "content": "",
          "media": {}
        }
      ],
      "id": "k_Reading_unit_04_lesson_05"
    },
    {
      "title": "Acting Like a Character",
      "bloom_level": "Analyze",
      "skills_tested": [],
      "steps": [
        {
          "type": "hook",
          "content": "",
          "media": {}
        },
        {
          "type": "concept",
          "content": "",
          "media": {}
        },
        {
          "type": "guided_practice",
          "content": "",
          "media": {}
        },
        {
          "type": "try_it",
          "content": "",
          "media": {}
        },
        {
          "type": "wrap_up",
          "content": "",
          "media": {}
        }
      ],
      "id": "k_Reading_unit_04_lesson_06"
    },
    {
      "title": "Comparing Two Characters",
      "bloom_level": "Apply",
      "skills_tested": [],
      "steps": [
        {
          "type": "hook",
          "content": "",
          "media": {}
        },
        {
          "type": "concept",
          "content": "",
          "media": {}
        },
        {
          "type": "guided_practice",
          "content": "",
          "media": {}
        },
        {
          "type": "try_it",
          "content": "",
          "media": {}
        },
        {
          "type": "wrap_up",
          "content": "",
          "media": {}
        }
      ],
      "id": "k_Reading_unit_04_lesson_07"
    },
    {
      "title": "Choosing Favorite Characters",
      "bloom_level": "Apply",
      "skills_tested": [],
      "steps": [
        {
          "type": "hook",
          "content": "",
          "media": {}
        },
        {
          "type": "concept",
          "content": "",
          "media": {}
        },
        {
          "type": "guided_practice",
          "content": "",
          "media": {}
        },
        {
          "type": "try_it",
          "content": "",
          "media": {}
        },
        {
          "type": "wrap_up",
          "content": "",
          "media": {}
        }
      ],
      "id": "k_Reading_unit_04_lesson_08"
    },
    {
      "title": "Exploring Good Guys and Bad Guys",
      "bloom_level": "Apply",
      "skills_tested": [],
      "steps": [
        {
          "type": "hook",
          "content": "",
          "media": {}
        },
        {
          "type": "concept",
          "content": "",
          "media": {}
        },
        {
          "type": "guided_practice",
          "content": "",
          "media": {}
        },
        {
          "type": "try_it",
          "content": "",
          "media": {}
        },
        {
          "type": "wrap_up",
          "content": "",
          "media": {}
        }
      ],
      "id": "k_Reading_unit_04_lesson_09"
    },
    {
      "title": "Making a Class Character Chart",
      "bloom_level": "Analyze",
      "skills_tested": [],
      "steps": [
        {
          "type": "hook",
          "content": "",
          "media": {}
        },
        {
          "type": "concept",
          "content": "",
          "media": {}
        },
        {
          "type": "guided_practice",
          "content": "",
          "media": {}
        },
        {
          "type": "try_it",
          "content": "",
          "media": {}
        },
        {
          "type": "wrap_up",
          "content": "",
          "media": {}
        }
      ],
      "id": "k_Reading_unit_04_lesson_10"
    },
    {
      "title": "Story Walk with Character Focus",
      "bloom_level": "Apply",
      "skills_tested": [],
      "steps": [
        {
          "type": "hook",
          "content": "",
          "media": {}
        },
        {
          "type": "concept",
          "content": "",
          "media": {}
        },
        {
          "type": "guided_practice",
          "content": "",
          "media": {}
        },
        {
          "type": "try_it",
          "content": "",
          "media": {}
        },
        {
          "type": "wrap_up",
          "content": "",
          "media": {}
        }
      ],
      "id": "k_Reading_unit_04_lesson_11"
    },
    {
      "title": "Creating a Character Puppet",
      "bloom_level": "Apply",
      "skills_tested": [],
      "steps": [
        {
          "type": "hook",
          "content": "",
          "media": {}
        },
        {
          "type": "concept",
          "content": "",
          "media": {}
        },
        {
          "type": "guided_practice",
          "content": "",
          "media": {}
        },
        {
          "type": "try_it",
          "content": "",
          "media": {}
        },
        {
          "type": "wrap_up",
          "content": "",
          "media": {}
        }
      ],
      "id": "k_Reading_unit_04_lesson_12"
    },
    {
      "title": "Writing Words to Describe Characters",
      "bloom_level": "Understand",
      "skills_tested": [],
      "steps": [
        {
          "type": "hook",
          "content": "",
          "media": {}
        },
        {
          "type": "concept",
          "content": "",
          "media": {}
        },
        {
          "type": "guided_practice",
          "content": "",
          "media": {}
        },
        {
          "type": "try_it",
          "content": "",
          "media": {}
        },
        {
          "type": "wrap_up",
          "content": "",
          "media": {}
        }
      ],
      "id": "k_Reading_unit_04_lesson_13"
    },
    {
      "title": "Making a Character Mask",
      "bloom_level": "Apply",
      "skills_tested": [],
      "steps": [
        {
          "type": "hook",
          "content": "",
          "media": {}
        },
        {
          "type": "concept",
          "content": "",
          "media": {}
        },
        {
          "type": "guided_practice",
          "content": "",
          "media": {}
        },
        {
          "type": "try_it",
          "content": "",
          "media": {}
        },
        {
          "type": "wrap_up",
          "content": "",
          "media": {}
        }
      ],
      "id": "k_Reading_unit_04_lesson_14"
    },
    {
      "title": "Writing and Drawing About a Character",
      "bloom_level": "Analyze",
      "skills_tested": [],
      "steps": [
        {
          "type": "hook",
          "content": "",
          "media": {}
        },
        {
          "type": "concept",
          "content": "",
          "media": {}
        },
        {
          "type": "guided_practice",
          "content": "",
          "media": {}
        },
        {
          "type": "try_it",
          "content": "",
          "media": {}
        },
        {
          "type": "wrap_up",
          "content": "",
          "media": {}
        }
      ],
      "id": "k_Reading_unit_04_lesson_15"
    },
    {
      "title": "Playing Who Am I? (Character Game)",
      "bloom_level": "Create",
      "skills_tested": [],
      "steps": [
        {
          "type": "hook",
          "content": "",
          "media": {}
        },
        {
          "type": "concept",
          "content": "",
          "media": {}
        },
        {
          "type": "guided_practice",
          "content": "",
          "media": {}
        },
        {
          "type": "try_it",
          "content": "",
          "media": {}
        },
        {
          "type": "wrap_up",
          "content": "",
          "media": {}
        }
      ],
      "id": "k_Reading_unit_04_lesson_16"
    },
    {
      "title": "Explaining Why We Like a Character",
      "bloom_level": "Analyze",
      "skills_tested": [],
      "steps": [
        {
          "type": "hook",
          "content": "",
          "media": {}
        },
        {
          "type": "concept",
          "content": "",
          "media": {}
        },
        {
          "type": "guided_practice",
          "content": "",
          "media": {}
        },
        {
          "type": "try_it",
          "content": "",
          "media": {}
        },
        {
          "type": "wrap_up",
          "content": "",
          "media": {}
        }
      ],
      "id": "k_Reading_unit_04_lesson_17"
    },
    {
      "title": "Character Walk Day",
      "bloom_level": "Evaluate",
      "skills_tested": [],
      "steps": [
        {
          "type": "hook",
          "content": "",
          "media": {}
        },
        {
          "type": "concept",
          "content": "",
          "media": {}
        },
        {
          "type": "guided_practice",
          "content": "",
          "media": {}
        },
        {
          "type": "try_it",
          "content": "",
          "media": {}
        },
        {
          "type": "wrap_up",
          "content": "",
          "media": {}
        }
      ],
      "id": "k_Reading_unit_04_lesson_18"
    },
    {
      "title": "Character Parade Practice",
      "bloom_level": "Apply",
      "skills_tested": [],
      "steps": [
        {
          "type": "hook",
          "content": "",
          "media": {}
        },
        {
          "type": "concept",
          "content": "",
          "media": {}
        },
        {
          "type": "guided_practice",
          "content": "",
          "media": {}
        },
        {
          "type": "try_it",
          "content": "",
          "media": {}
        },
        {
          "type": "wrap_up",
          "content": "",
          "media": {}
        }
      ],
      "id": "k_Reading_unit_04_lesson_19"
    },
    {
      "title": "Classroom Character Parade",
      "bloom_level": "Create",
      "skills_tested": [],
      "steps": [
        {
          "type": "hook",
          "content": "",
          "media": {}
        },
        {
          "type": "concept",
          "content": "",
          "media": {}
        },
        {
          "type": "guided_practice",
          "content": "",
          "media": {}
        },
        {
          "type": "try_it",
          "content": "",
          "media": {}
        },
        {
          "type": "wrap_up",
          "content": "",
          "media": {}
        }
      ],
      "id": "k_Reading_unit_04_lesson_20"
    }
  ],
  "id": "k_Reading_unit_04"
}